datamini_toolkits/__init__.py
datamini_toolkits/tests.py
datamini_toolkits/cmysql/__init__.py
datamini_toolkits/cmysql/agent.py
datamini_toolkits/cmysql/cli.py
datamini_toolkits/cmysql/logs.py
datamini_toolkits/cmysql/prompts.py
datamini_toolkits/mock_data/__init__.py
datamini_toolkits/mock_data/agent.py
datamini_toolkits/mock_data/base.py
datamini_toolkits/mock_data/cli.py
datamini_toolkits/mock_data/logs.py
datamini_toolkits/mock_data/prompts.py
datamini_toolkits/mock_data/test_tools.py
datamini_toolkits/mock_data/tools.py
datamini_toolkits/sql_data_maker/__init__.py
datamini_toolkits/sql_data_maker/agent.py
datamini_toolkits/sql_data_maker/base.py
datamini_toolkits/sql_data_maker/cli.py
datamini_toolkits/sql_data_maker/logs.py
datamini_toolkits/sql_data_maker/prompts.py
datamini_toolkits/sql_data_maker/test_tools.py
datamini_toolkits/sql_data_maker/tools.py
datamini_toolkits-0.1.7.dist-info/METADATA
datamini_toolkits-0.1.7.dist-info/WHEEL
datamini_toolkits-0.1.7.dist-info/entry_points.txt
datamini_toolkits-0.1.7.dist-info/top_level.txt
datamini_toolkits-0.1.7.dist-info/RECORD
