Metadata-Version: 2.1
Name: datamini-toolkits
Version: 0.1.7
Summary: A toolkit for Data Using AI(e.g. LLM) by DataMini
Author: DataMini
